betatest/__init__.py
betatest/amtest.py
betatest/amtest_example.py
betatest/version.py
betatest-0.1.0.dist-info/METADATA
betatest-0.1.0.dist-info/RECORD
betatest-0.1.0.dist-info/WHEEL
betatest-0.1.0.dist-info/top_level.txt
