Metadata-Version: 2.1
Name: betatest
Version: 0.1.0
Summary: Testing helpers for Python 3.6+.
Home-page: https://gitlab.com/b5/betatest
Author: Paul Barker
Author-email: paul@betafive.co.uk
License: Apache License 2.0
Platform: Any
Classifier: Development Status :: 3 - Alpha
Classifier: Intended Audience :: Developers
Classifier: License :: OSI Approved :: Apache Software License
Classifier: Operating System :: OS Independent
Classifier: Programming Language :: Python :: 3
Classifier: Topic :: Software Development :: Testing
Requires-Python: >=3.6
